README.md
setup.py
rc522/__init__.py
rc522/rfid.py
rc522.egg-info/PKG-INFO
rc522.egg-info/SOURCES.txt
rc522.egg-info/dependency_links.txt
rc522.egg-info/top_level.txt