Metadata-Version: 2.1
Name: rc522
Version: 0.0.1.5
Summary: RFID Utility
Home-page: https://github.com/Tsangares/rc522
Author-email: william.wyatt@cgu.edu
License: UNKNOWN
Platform: UNKNOWN
Classifier: Programming Language :: Python :: 3
Classifier: License :: OSI Approved :: MIT License
Classifier: Operating System :: OS Independent
Requires-Python: >=3.7
